rgbkb/__init__.py
rgbkb/__main__.py
rgbkb/cli.py
rgbkb/kb.py
rgbkb/utils.py
rgbkb/acer_ph16_71/README.md
rgbkb/acer_ph16_71/__init__.py
rgbkb/acer_ph16_71/commands.py
rgbkb/acer_ph16_71/device.py
rgbkb/acer_ph16_71/keys.py
rgbkb-0.0.1.dist-info/METADATA
rgbkb-0.0.1.dist-info/WHEEL
rgbkb-0.0.1.dist-info/entry_points.txt
rgbkb-0.0.1.dist-info/licenses/LICENSE
rgbkb-0.0.1.dist-info/RECORD
