Metadata-Version: 2.4
Name: rgbkb
Version: 0.0.1
Summary: App and library to control RGB keyboard backlight
Project-URL: Homepage, https://github.com/fuho/rgbkb
Project-URL: Issues, https://github.com/fuho/rgbkb/issues
Author-email: Ondrej Dolejsi <ondrej.dolejsi@gmail.com>
License-File: LICENSE
Classifier: License :: OSI Approved :: GNU General Public License v3 (GPLv3)
Classifier: License :: Public Domain
Classifier: Natural Language :: English
Classifier: Operating System :: POSIX :: Linux
Classifier: Programming Language :: Python :: 3
Classifier: Programming Language :: Python :: 3.8
Classifier: Programming Language :: Python :: 3.9
Classifier: Programming Language :: Python :: 3.10
Classifier: Programming Language :: Python :: 3.11
Classifier: Programming Language :: Python :: 3.12
Classifier: Programming Language :: Python :: 3.13
Classifier: Topic :: Multimedia :: Graphics :: Presentation
Classifier: Topic :: System
Classifier: Topic :: System :: Hardware
Classifier: Topic :: System :: Hardware :: Universal Serial Bus (USB)
Classifier: Topic :: System :: Hardware :: Universal Serial Bus (USB) :: Human Interface Device (HID)
Classifier: Topic :: System :: Hardware :: Universal Serial Bus (USB) :: Miscellaneous
Classifier: Topic :: Utilities
Classifier: Typing :: Typed
Requires-Python: >=3.8
Requires-Dist: usbx==0.8.1
Provides-Extra: dev
Requires-Dist: pytest; extra == 'dev'
